Workbook

Sheet Assumptions
B2: Item | C2: Value
B3: Annual Rent (Initial) | C3: 24000
B4: Monthly Rent | C4: 2000
B5: Monthly Mortgage | C5: 900
B6: Start Month | C6: 46023
B7: End Month | C7: 46387

Sheet Prepayment Schedule
B3: 46023 | C3: 46054 | D3: 46082 | E3: 46113 | F3: 46143 | G3: 46174 | H3: 46204 | I3: 46235 | J3: 46266 | K3: 46296 | L3: 46327 | M3: 46357
A4: Opening Prepayment Balance | B4: =Assumptions!C3 -> 24000 | C4: =B8 -> 22000 | D4: =C8 -> 20000 | E4: =D8 -> 18000 | F4: =E8 -> 16000 | G4: =F8 -> 14000 | H4: =G8 -> 12000 | I4: =H8 -> 10000 | J4: =I8 -> 8000 | ... M4: =L8 -> 2000
A6: Rent Expense | B6: =Assumptions!$C$4 -> 2000 | C6: =Assumptions!$C$4 -> 2000 | D6: =Assumptions!$C$4 -> 2000 | E6: =Assumptions!$C$4 -> 2000 | F6: =Assumptions!$C$4 -> 2000 | G6: =Assumptions!$C$4 -> 2000 | H6: =Assumptions!$C$4 -> 2000 | I6: =Assumptions!$C$4 -> 2000 | ... M6: =Assumptions!$C$4 -> 2000
A8: Closing Prepayment Balance | B8: =B4-B6 -> 22000 | C8: =C4-C6 -> 20000 | D8: =D4-D6 -> 18000 | E8: =E4-E6 -> 16000 | F8: =F4-F6 -> 14000 | G8: =G4-G6 -> 12000 | H8: =H4-H6 -> 10000 | I8: =I4-I6 -> 8000 | ... M8: =M4-M6 -> 0
A12: Control | B12: Value
A13: Total Rent Expensed | B13: =SUM(B6:M6) -> 24000
A14: Annual Rent Paid | B14: =Assumptions!C3 -> 24000
A15: Difference | B15: =B13-B14 -> 0

Sheet Monthly Profit & Loss (P&L)
C3: 46023 | D3: 46054 | E3: 46082 | F3: 46113 | G3: 46143 | H3: 46174 | I3: 46204 | J3: 46235 | K3: 46266 | L3: 46296 | M3: 46327 | N3: 46357
B4: Rent Expense | C4: =Assumptions!$C$4 -> 2000 | D4: =Assumptions!$C$4 -> 2000 | E4: =Assumptions!$C$4 -> 2000 | F4: =Assumptions!$C$4 -> 2000 | G4: =Assumptions!$C$4 -> 2000 | H4: =Assumptions!$C$4 -> 2000 | I4: =Assumptions!$C$4 -> 2000 | J4: =Assumptions!$C$4 -> 2000 | ... N4: =Assumptions!$C$4 -> 2000
B6: Mortgage Expense | C6: =Assumptions!$C$5 -> 900 | D6: =Assumptions!$C$5 -> 900 | E6: =Assumptions!$C$5 -> 900 | F6: =Assumptions!$C$5 -> 900 | G6: =Assumptions!$C$5 -> 900 | H6: =Assumptions!$C$5 -> 900 | I6: =Assumptions!$C$5 -> 900 | J6: =Assumptions!$C$5 -> 900 | ... N6: =Assumptions!$C$5 -> 900
B8: Operating Profit | C8: =C4-C6 -> 1100 | D8: =D4-D6 -> 1100 | E8: =E4-E6 -> 1100 | F8: =F4-F6 -> 1100 | G8: =G4-G6 -> 1100 | H8: =H4-H6 -> 1100 | I8: =I4-I6 -> 1100 | J8: =J4-J6 -> 1100 | ... N8: =N4-N6 -> 1100
B10: Total | C10: =SUM(C8:N8) -> 13200

Sheet Balance Sheet
C3: 46023 | D3: 46054 | E3: 46082 | F3: 46113 | G3: 46143 | H3: 46174 | I3: 46204 | J3: 46235 | K3: 46266 | L3: 46296 | M3: 46327 | N3: 46357
B4: Assets
B5: Prepayments | C5: ='Prepayment Schedule'!B8 -> 22000 | D5: ='Prepayment Schedule'!C8 -> 20000 | E5: ='Prepayment Schedule'!D8 -> 18000 | F5: ='Prepayment Schedule'!E8 -> 16000 | G5: ='Prepayment Schedule'!F8 -> 14000 | H5: ='Prepayment Schedule'!G8 -> 12000 | I5: ='Prepayment Schedule'!H8 -> 10000 | J5: ='Prepayment Schedule'!I8 -> 8000 | ... N5: ='Prepayment Schedule'!M8 -> 0
B6: Equity
B7: Earnings | C7: ='Monthly Profit & Loss (P&L)'!C8 -> 1100 | D7: ='Monthly Profit & Loss (P&L)'!D8+C7 -> 2200 | E7: ='Monthly Profit & Loss (P&L)'!E8+D7 -> 3300 | F7: ='Monthly Profit & Loss (P&L)'!F8+E7 -> 4400 | G7: ='Monthly Profit & Loss (P&L)'!G8+F7 -> 5500 | H7: ='Monthly Profit & Loss (P&L)'!H8+G7 -> 6600 | I7: ='Monthly Profit & Loss (P&L)'!I8+H7 -> 7700 | J7: ='Monthly Profit & Loss (P&L)'!J8+I7 -> 8800 | K7: ='Monthly Profit & Loss (P&L)'!K8+J7 -> 9900 | ... N7: ='Monthly Profit & Loss (P&L)'!N8+M7 -> 13200
